stsmd/__init__.py
stsmd-0.0.6.dist-info/LICENSE
stsmd-0.0.6.dist-info/METADATA
stsmd-0.0.6.dist-info/WHEEL
stsmd-0.0.6.dist-info/top_level.txt
stsmd-0.0.6.dist-info/RECORD
