Metadata-Version: 2.1
Name: stsmd
Version: 0.0.6
Summary: A small package to get closest text document with SMD and Sentence transformers embeddings
Home-page: https://github.com/pypa/sampleproject
Author: Alice Petit, Nolwenn Sourice
License: UNKNOWN
Platform: UNKNOWN
Classifier: Programming Language :: Python :: 3
Classifier: License :: OSI Approved :: MIT License
Classifier: Operating System :: OS Independent
Requires-Python: >=3.6
